{
    "room_display_id": 7688602,
    "room_real_id": 7688602,
    "type": "POPULARITY_RED_POCKET_WINNER_LIST",
    "data": {
        "cmd": "POPULARITY_RED_POCKET_WINNER_LIST",
        "data": {
            "lot_id": 7004016,
            "total_num": 38,
            "winner_info": [
                [
                    28122658,
                    "我不说话但我不哑",
                    3859875,
                    31215
                ],
                [
                    471243587,
                    "夕语应泷",
                    3818443,
                    30971
                ],
                [
                    97007382,
                    "一条水煮鱼Yuu",
                    3851766,
                    30971
                ],
                [
                    8977859,
                    "轨迹术士",
                    3833419,
                    30971
                ],
                [
                    1205922065,
                    "近在哈哈哈哈",
                    3835876,
                    31278
                ],
                [
                    109170111,
                    "TSJST",
                    3821210,
                    31278
                ],
                [
                    44380639,
                    "刘姥姥再试云雨情",
                    3832877,
                    31278
                ],
                [
                    49445718,
                    "月羽下",
                    3859876,
                    31278
                ],
                [
                    470800120,
                    "回复二月",
                    3868314,
                    31278
                ],
                [
                    233121047,
                    "o_王不留行_O",
                    3818444,
                    31278
                ],
                [
                    346929120,
                    "不高兴的魔女",
                    3867885,
                    31278
                ],
                [
                    6852429,
                    "丢人丶瓜皮",
                    3833420,
                    31278
                ],
                [
                    397629102,
                    "伏家の小剑灵",
                    3851767,
                    31278
                ],
                [
                    11503745,
                    "大王DAD",
                    3835310,
                    31278
                ],
                [
                    6332237,
                    "呼叫沙滩2",
                    3818445,
                    31278
                ],
                [
                    94364265,
                    "蛮飞升邪",
                    3835877,
                    31278
                ],
                [
                    40745206,
                    "Saber-妮可",
                    3868046,
                    31278
                ],
                [
                    22679461,
                    "冬眠了886",
                    3821211,
                    31278
                ],
                [
                    107954692,
                    "酸辣天使腌入味",
                    3851768,
                    31278
                ],
                [
                    29685501,
                    "融化在音乐的跳伞指挥",
                    3821212,
                    31278
                ],
                [
                    35167142,
                    "颠也不颠",
                    3851769,
                    31278
                ],
                [
                    1217759838,
                    "视我的觉",
                    3859300,
                    31278
                ],
                [
                    25732829,
                    "真有你的啊edg",
                    3833421,
                    31278
                ],
                [
                    267339,
                    "wzc1111",
                    3833422,
                    31278
                ],
                [
                    197852568,
                    "追忆往o昔时光",
                    3859877,
                    31278
                ],
                [
                    18885290,
                    "这个名字我tm想了好久",
                    3868315,
                    31278
                ],
                [
                    93569311,
                    "谁可称无敌",
                    3821213,
                    31278
                ],
                [
                    19997308,
                    "请吃掉墨小樱吧",
                    3859878,
                    31278
                ],
                [
                    39101023,
                    "总是如此这般",
                    3850008,
                    31278
                ],
                [
                    259444069,
                    "私は沐風様です",
                    3833423,
                    31278
                ],
                [
                    35722758,
                    "謦川",
                    3859756,
                    31278
                ],
                [
                    210414341,
                    "阿墨君墨酱",
                    3821214,
                    31278
                ],
                [
                    473803397,
                    "白鹭姬Shirasagihime",
                    3818446,
                    31278
                ],
                [
                    313818486,
                    "寒暄の寒暄",
                    3868047,
                    31278
                ],
                [
                    2615385,
                    "双木精灵",
                    3835878,
                    31278
                ],
                [
                    283848096,
                    "望月伢",
                    3867797,
                    31278
                ],
                [
                    2446144,
                    "终将成为大贤者",
                    3813917,
                    31278
                ],
                [
                    249199515,
                    "blibli643794",
                    3835676,
                    31278
                ]
            ],
            "awards": {
                "30971": {
                    "award_type": 1,
                    "award_name": "这个好诶",
                    "award_pic": "https://s1.hdslb.com/bfs/live/bb6c11dcc365b3d8287569f08b8b0d0f2e1a3ef8.png",
                    "award_big_pic": "https://i0.hdslb.com/bfs/live/dafd2e9e5c3086377124a9328e840cd21a3f6847.png",
                    "award_price": 1000
                },
                "31215": {
                    "award_type": 1,
                    "award_name": "花式夸夸",
                    "award_pic": "https://s1.hdslb.com/bfs/live/28186596880db45a7b843f17d6ebb70feeac06f9.png",
                    "award_big_pic": "https://i0.hdslb.com/bfs/live/a6d07ef70487c4c6f7b328b2a5d8838e0841482a.png",
                    "award_price": 33000
                },
                "31278": {
                    "award_type": 1,
                    "award_name": "打call",
                    "award_pic": "https://s1.hdslb.com/bfs/live/461be640f60788c1d159ec8d6c5d5cf1ef3d1830.png",
                    "award_big_pic": "https://i0.hdslb.com/bfs/live/9e6521c57f24c7149c054d265818d4b82059f2ef.png",
                    "award_price": 500
                }
            },
            "version": 1
        }
    }
}